vect/__init__.py
vect/vector.py
vect-0.0.7.dist-info/LICENSE.txt
vect-0.0.7.dist-info/METADATA
vect-0.0.7.dist-info/WHEEL
vect-0.0.7.dist-info/top_level.txt
vect-0.0.7.dist-info/RECORD
