Metadata-Version: 2.1
Name: vect
Version: 0.0.7
Summary: This powerful tool can help you in vector related work in python
Home-page: https://github.com/ALEJORIOS/vect.git
Author: Alejandro Ríos
Author-email: UNKNOWN
License: UNKNOWN
Keywords: vect,vector,algebra
Platform: UNKNOWN
